shoydokova/__init__.py
shoydokova/core.py
shoydokova/periodic.py
shoydokova-0.8.2.dist-info/METADATA
shoydokova-0.8.2.dist-info/WHEEL
shoydokova-0.8.2.dist-info/top_level.txt
shoydokova-0.8.2.dist-info/RECORD
