Metadata-Version: 2.1
Name: shoydokova
Version: 0.8.2
Summary: A fun API for generating jokes and funny facts
Home-page: https://github.com/snexha/Sheg
Author: Snezha
Author-email: YlC9L@example.com
Requires-Python: >=3.6
